photod/__init__.py
photod/_version.py
photod/example_module.py
photod-0.0.1.dist-info/LICENSE
photod-0.0.1.dist-info/METADATA
photod-0.0.1.dist-info/WHEEL
photod-0.0.1.dist-info/top_level.txt
photod-0.0.1.dist-info/RECORD
