Metadata-Version: 2.1
Name: photod
Version: 0.0.1
Author-email: Lovro Palaversa <lp@irb.hr>
License: BSD 3-Clause License
Project-URL: Source Code, https://github.com/labastro-rbi/photod
Classifier: Development Status :: 4 - Beta
Classifier: License :: OSI Approved :: BSD License
Classifier: Intended Audience :: Developers
Classifier: Intended Audience :: Science/Research
Classifier: Operating System :: OS Independent
Classifier: Programming Language :: Python
Requires-Python: >=3.10
License-File: LICENSE
Provides-Extra: dev
Requires-Dist: jupyter ; extra == 'dev'
Requires-Dist: pre-commit ; extra == 'dev'
Requires-Dist: pytest ; extra == 'dev'
Requires-Dist: pytest-cov ; extra == 'dev'
